rthon/__init__.py
rthon/__main__.py
rthon/binomial.py
rthon/exponential.py
rthon/gamma.py
rthon/normal.py
rthon/poisson.py
rthon/uniform.py
rthon-0.3.0.dist-info/METADATA
rthon-0.3.0.dist-info/WHEEL
rthon-0.3.0.dist-info/entry_points.txt
rthon-0.3.0.dist-info/licenses/LICENSE
rthon-0.3.0.dist-info/RECORD
