Metadata-Version: 2.4
Name: rthon
Version: 0.3.0
Summary: R-style probability functions for Python: Normal, Uniform, Binomial, Poisson, Exponential, and Gamma distributions
Project-URL: Homepage, https://github.com/sdswitz/rthon
Author-email: Sam Switz <samuel76@illinois.edu>
License: MIT
License-File: LICENSE
Keywords: R,binomial,distributions,exponential,gamma,normal,poisson,probability,statistics,uniform
Classifier: Intended Audience :: Science/Research
Classifier: License :: OSI Approved :: MIT License
Classifier: Programming Language :: Python :: 3
Classifier: Topic :: Scientific/Engineering :: Mathematics
Requires-Python: >=3.8
Provides-Extra: dev
Requires-Dist: black; extra == 'dev'
Requires-Dist: build; extra == 'dev'
Requires-Dist: hypothesis; extra == 'dev'
Requires-Dist: pytest; extra == 'dev'
Requires-Dist: ruff; extra == 'dev'
Requires-Dist: twine; extra == 'dev'
